rich_cli/__init__.py
rich_cli/__main__.py
rich_cli/markdown.py
rich_cli/pager.py
rich_cli/win_vt.py
rich_cli-1.8.1.dist-info/LICENSE
rich_cli-1.8.1.dist-info/METADATA
rich_cli-1.8.1.dist-info/WHEEL
rich_cli-1.8.1.dist-info/entry_points.txt
rich_cli-1.8.1.dist-info/RECORD
