Metadata-Version: 2.3
Name: rich-cli
Version: 1.8.1
Summary: Command Line Interface to Rich
License: MIT
Author: Will McGugan
Author-email: willmcgugan@gmail.com
Requires-Python: >=3.9
Classifier: Development Status :: 5 - Production/Stable
Classifier: Environment :: Console
Classifier: Intended Audience :: Developers
Classifier: Operating System :: Microsoft :: Windows
Classifier: Operating System :: MacOS
Classifier: Operating System :: POSIX :: Linux
Classifier: Programming Language :: Python :: 3.9
Classifier: Programming Language :: Python :: 3.10
Classifier: Programming Language :: Python :: 3.11
Classifier: Programming Language :: Python :: 3.12
Classifier: Programming Language :: Python :: 3.13
Requires-Dist: click (>=8.0.0,<9.0.0)
Requires-Dist: requests (>=2.0.0,<3.0.0)
Requires-Dist: rich (>=12.4.0,<13.0.0)
Requires-Dist: rich-rst (>=1.1.7,<2.0.0)
Requires-Dist: textual (>=0.1.18,<0.2.0)
Project-URL: Homepage, https://github.com/Textualize/rich-cli
